{
  "id": 3,
  "title": "আব্বাস ব্যতীত বাড়ির প্রত্যেকের মুখে ঔষধ ঢাল তা আমি দেখি",
  "subTitle": "ওফাতপূর্ব অসুস্থতায় নবীজী ﷺ-এর মুখে ওষুধ ঢালা এবং ঘরের সবাইকে কিসাস",
  "slug": "prophet-last-illness-medicine-ledud",
  "year": "11",
  "enlist_author": "Irshad Hossain",
  "enlist_date": "June 21, 2026",
  "book_name": "সহীহ বুখারী",
  "arabic_script": "حديث عَائِشَةَ، قَالَتْ: لَدَدْنَاهُ فِي مَرَضِهِ، فَجَعَلَ يُشِيرُ إِلَيْنَا أَنْ لاَ تَلُدُّونِي فَقُلْنَا: كَرَاهِيَةُ الْمَرِيضِ لِلدَّوَاءِ فَلَمَّا أَفَاقَ، قَالَ: أَلَمْ أَنْهَكُمْ أَنْ تَلدُّونِي قُلْنَا: كَرَاهِيَةَ الْمَرِيضِ لِلدَّوَاءِ فَقَالَ لاَ يَبْقَى أَحَدٌ فِي الْبَيْتِ إِلاَّ لُدَّ وَأَنَا أَنْظرُ، إِلاَّ الْعَبَّاسَ، فَإِنَّهُ لَمْ يَشْهَدْكُمْ",
  "bangla_script": "নবী ﷺ-এর অসুস্থতার সময় আমরা তাঁর মুখে (লাদূদ পদ্ধতিতে) ওষুধ দিয়েছিলাম। তখন তিনি আমাদের দিকে ইশারা করে বোঝাতে লাগলেন যে, ‘তোমরা আমার মুখে ওষুধ দিও না।’\n\nআমরা বললাম, ‘এ তো রোগীর ওষুধের প্রতি স্বাভাবিক অনীহা।’\n\nপরে যখন তিনি চেতনা ফিরে পেলেন, তখন বললেন:\n\n‘আমি কি তোমাদেরকে আমার মুখে ওষুধ দিতে নিষেধ করিনি?’\n\nআমরা বললাম, ‘আমরা ভেবেছিলাম, এটি রোগীর ওষুধের প্রতি স্বাভাবিক অনীহা।’\n\nতখন তিনি বললেন:\n\n‘এই ঘরে যে-ই আছে, তার মুখে অবশ্যই এই ওষুধ দেওয়া হবে, আর আমি তা দেখব; তবে আব্বাস ব্যতীত, কারণ তিনি তোমাদের সঙ্গে উপস্থিত ছিলেন না (বা তোমাদের এ কাজে অংশগ্রহণ করেননি)।’",
  "chain_of_narrator": [
    {
      "name": "উম্মুল মুমিনীন হযরত আয়েশা",
      "weight": 10,
      "Note": ""
    }
  ],
  "links": [
    {
      "text": "Hadith BD Online",
      "url": "https://www.hadithbd.com/hadith/link/?id=84655"
    }
  ],
  "tags": [
    "ওফাত",
    "রাগান্বিত",
    "ওফাতের পূর্বে"
  ]
}